matched_betting_calculator/__init__.py
matched_betting_calculator/base.py
matched_betting_calculator/bet.py
matched_betting_calculator/constants.py
matched_betting_calculator/errors.py
matched_betting_calculator/factory.py
matched_betting_calculator/utils.py
matched_betting_calculator/back_lay_strategy/__init__.py
matched_betting_calculator/back_lay_strategy/back_lay_accumulated_calculator.py
matched_betting_calculator/back_lay_strategy/back_lay_simple_calculator.py
matched_betting_calculator/dutching_strategy/__init__.py
matched_betting_calculator/dutching_strategy/dutching_simple_calculator.py
matched_betting_calculator-0.2.0.dist-info/METADATA
matched_betting_calculator-0.2.0.dist-info/WHEEL
matched_betting_calculator-0.2.0.dist-info/top_level.txt
matched_betting_calculator-0.2.0.dist-info/RECORD
