Metadata-Version: 2.4
Name: matched_betting_calculator
Version: 0.2.0
Summary: Matched betting calculators using back-lay and dutching strategies
Author-email: Gabriel Alfonsín Espín <gabriel.alfonsin.espin@gmail.com>
License: MIT
Project-URL: Homepage, https://github.com/oplaco/matched-betting-calculator
Requires-Python: >=3.8
Requires-Dist: sympy>=1.14
